[
  {
    "dateStr": "Jeudi 16 Avril",
    "timestamp": 1776290400000,
    "postes": [
      {
        "medecin": "GA",
        "poste": "P",
        "telephone": "666311467"
      },
      {
        "medecin": "JE",
        "poste": "Réa 1°",
        "telephone": "+33670721095"
      },
      {
        "medecin": "MSK",
        "poste": "Réa 2°",
        "telephone": "+33668110285"
      },
      {
        "medecin": "LB",
        "poste": "Réa 3°",
        "telephone": null
      },
      {
        "medecin": "MS",
        "poste": "ECMO",
        "telephone": "687691545"
      },
      {
        "medecin": "MM",
        "poste": "Ao",
        "telephone": "659568451"
      },
      {
        "medecin": "PGU",
        "poste": "An 1°",
        "telephone": "633808923"
      },
      {
        "medecin": "IB",
        "poste": "An 2°",
        "telephone": null
      },
      {
        "medecin": "JM",
        "poste": "An 3°",
        "telephone": null
      },
      {
        "medecin": "FB",
        "poste": "An 4°",
        "telephone": "630092616"
      },
      {
        "medecin": "MS",
        "poste": "EXT",
        "telephone": "687691545"
      }
    ]
  },
  {
    "dateStr": "Vendredi 17 Avril",
    "timestamp": 1776376800000,
    "postes": [
      {
        "medecin": "MSK",
        "poste": "P",
        "telephone": "+33668110285"
      },
      {
        "medecin": "TR",
        "poste": "Réa 1°",
        "telephone": "613835189"
      },
      {
        "medecin": "CBL",
        "poste": "Réa 2°",
        "telephone": "+33620439868"
      },
      {
        "medecin": "LB",
        "poste": "Réa 3°",
        "telephone": null
      },
      {
        "medecin": "JM",
        "poste": "ECMO",
        "telephone": null
      },
      {
        "medecin": "JE",
        "poste": "AC",
        "telephone": "+33670721095"
      },
      {
        "medecin": "FB",
        "poste": "Ao",
        "telephone": "630092616"
      },
      {
        "medecin": "JM",
        "poste": "An 1°",
        "telephone": null
      },
      {
        "medecin": "AU",
        "poste": "An 2°",
        "telephone": "622054893"
      },
      {
        "medecin": "PGU",
        "poste": "An 3°",
        "telephone": "633808923"
      },
      {
        "medecin": "RC",
        "poste": "An 4°",
        "telephone": "689644044"
      }
    ]
  },
  {
    "dateStr": "Samedi 18 Avril",
    "timestamp": 1776463200000,
    "postes": [
      {
        "medecin": "CBL",
        "poste": "P",
        "telephone": "+33620439868"
      },
      {
        "medecin": "FB",
        "poste": "ECMO",
        "telephone": "630092616"
      },
      {
        "medecin": "JM",
        "poste": "Ao",
        "telephone": null
      }
    ]
  },
  {
    "dateStr": "Dimanche 19 Avril",
    "timestamp": 1776549600000,
    "postes": [
      {
        "medecin": "MSK",
        "poste": "P",
        "telephone": "+33668110285"
      },
      {
        "medecin": "JM",
        "poste": "ECMO",
        "telephone": null
      },
      {
        "medecin": "FB",
        "poste": "Ao",
        "telephone": "630092616"
      }
    ]
  },
  {
    "dateStr": "Lundi 20 Avril",
    "timestamp": 1776636000000,
    "postes": [
      {
        "medecin": "MS",
        "poste": "P",
        "telephone": "687691545"
      },
      {
        "medecin": "LB",
        "poste": "Réa 1°",
        "telephone": null
      },
      {
        "medecin": "GA",
        "poste": "Réa 2°",
        "telephone": "666311467"
      },
      {
        "medecin": "RC",
        "poste": "Réa 3°",
        "telephone": "689644044"
      },
      {
        "medecin": "EC",
        "poste": "ECMO",
        "telephone": "630817301"
      },
      {
        "medecin": "PG",
        "poste": "AC",
        "telephone": "+33661761783"
      },
      {
        "medecin": "BB",
        "poste": "Ao",
        "telephone": "618093554"
      },
      {
        "medecin": "EC",
        "poste": "An 1°",
        "telephone": "630817301"
      },
      {
        "medecin": "TR",
        "poste": "An 2°",
        "telephone": "613835189"
      },
      {
        "medecin": "MM",
        "poste": "An 3°",
        "telephone": "659568451"
      },
      {
        "medecin": "CBL",
        "poste": "An 4°",
        "telephone": "+33620439868"
      },
      {
        "medecin": "IB",
        "poste": "EXT",
        "telephone": null
      }
    ]
  },
  {
    "dateStr": "Mardi 21 Avril",
    "timestamp": 1776722400000,
    "postes": [
      {
        "medecin": "JE",
        "poste": "P",
        "telephone": "+33670721095"
      },
      {
        "medecin": "LO",
        "poste": "Réa 1°",
        "telephone": null
      },
      {
        "medecin": "NZ",
        "poste": "Réa 2°",
        "telephone": "684310734"
      },
      {
        "medecin": "RC",
        "poste": "Réa 3°",
        "telephone": "689644044"
      },
      {
        "medecin": "NZ",
        "poste": "ECMO",
        "telephone": "684310734"
      },
      {
        "medecin": "TR",
        "poste": "Ao",
        "telephone": "613835189"
      },
      {
        "medecin": "IB",
        "poste": "An 1°",
        "telephone": null
      },
      {
        "medecin": "GA",
        "poste": "An 2°",
        "telephone": "666311467"
      },
      {
        "medecin": "PG",
        "poste": "An 3°",
        "telephone": "+33661761783"
      },
      {
        "medecin": "JM",
        "poste": "An 5°",
        "telephone": null
      },
      {
        "medecin": "CBL",
        "poste": "EXT",
        "telephone": "+33620439868"
      }
    ]
  },
  {
    "dateStr": "Mercredi 22 Avril",
    "timestamp": 1776808800000,
    "postes": [
      {
        "medecin": "LO",
        "poste": "P",
        "telephone": null
      },
      {
        "medecin": "NZ",
        "poste": "Réa 1°",
        "telephone": "684310734"
      },
      {
        "medecin": "GA",
        "poste": "Réa 2°",
        "telephone": "666311467"
      },
      {
        "medecin": "RC",
        "poste": "Réa 3°",
        "telephone": "689644044"
      },
      {
        "medecin": "BB",
        "poste": "ECMO",
        "telephone": "618093554"
      },
      {
        "medecin": "PG",
        "poste": "AC",
        "telephone": "+33661761783"
      },
      {
        "medecin": "JM",
        "poste": "Ao",
        "telephone": null
      },
      {
        "medecin": "BB",
        "poste": "An 1°",
        "telephone": "618093554"
      },
      {
        "medecin": "MM",
        "poste": "An 2°",
        "telephone": "659568451"
      },
      {
        "medecin": "IB",
        "poste": "An 3°",
        "telephone": null
      },
      {
        "medecin": "EC",
        "poste": "An 4°",
        "telephone": "630817301"
      },
      {
        "medecin": "MSK",
        "poste": "EXT",
        "telephone": "+33668110285"
      }
    ]
  }
]